uking_saves/__init__.py
uking_saves/gamedata.json
uking_saves-0.1.0.dist-info/METADATA
uking_saves-0.1.0.dist-info/WHEEL
uking_saves-0.1.0.dist-info/top_level.txt
uking_saves-0.1.0.dist-info/RECORD
