Metadata-Version: 2.1
Name: uking-saves
Version: 0.1.0
Summary: Parse and modify BOTW save files
Home-page: https://github.com/NiceneNerd/uking-saves/
Author: NiceneNerd
Author-email: email@calebdixonsmith.top
License: GPLv3
Platform: UNKNOWN
Classifier: Development Status :: 4 - Beta
Classifier: License :: OSI Approved :: GNU General Public License v3 or later (GPLv3+)
Classifier: Programming Language :: Python :: 3.7
Requires-Python: >=3.7
